Metadata-Version: 2.4
Name: adafruit-circuitpython-ticks
Version: 1.1.5
Summary: Work with intervals and deadlines in milliseconds
Author-email: Adafruit Industries <circuitpython@adafruit.com>
License: MIT
Project-URL: Homepage, https://github.com/adafruit/Adafruit_CircuitPython_ticks.git
Keywords: adafruit,blinka,circuitpython,micropython,ticks,time,clock,deadline,interval
Classifier: Intended Audience :: Developers
Classifier: Topic :: Software Development :: Libraries
Classifier: Topic :: Software Development :: Embedded Systems
Classifier: Topic :: System :: Hardware
Classifier: License :: OSI Approved :: MIT License
Classifier: Programming Language :: Python :: 3
License-File: LICENSE
Requires-Dist: Adafruit-Blinka
Provides-Extra: optional
Dynamic: license-file
